{
  "stage_id": "STAGE-049",
  "verdict": "PASS",
  "summary": "Faction schisms and survivor politics successfully modeled, implemented, and validated. The system now supports procedural political split events, splinter group formation, and auditable reconciliation paths while strictly prohibiting permanent social exile or player government.",
  "checks": {
    "schism_boundary_defined": true,
    "schism_contract_validates": true,
    "schism_generation_stub_passes": true,
    "splinter_blocs_recoverable": true,
    "political_recovery_possible": true,
    "tower_attention_tradeoff_preserved": true,
    "dashboard_schism_evidence_passes": true,
    "no_permanent_government_or_social_exile_created": true
  }
}
