{
  "stage_id": "STAGE-034",
  "verdict": "PASS",
  "summary": "Physical USB flashing handoff and safety gate successfully modeled, implemented, and validated. The system now enforces strict internal disk rejection, explicit operator acknowledgment via confirmation phrases, and dry-run planning for artifact delivery.",
  "checks": {
    "usb_handoff_boundary_defined": true,
    "device_contract_validates": true,
    "read_only_device_enumeration_passes": true,
    "internal_host_disks_rejected": true,
    "dry_run_flash_plan_passes": true,
    "operator_acknowledgment_gate_passes": true,
    "artifact_hash_validation_passes": true,
    "admin_terminal_usb_handoff_reporting_passes": true,
    "no_device_writes_possible_by_default": true
  }
}
