{
  "patch_id": "TOWER-ENGINE-001",
  "verdict": "PASS",
  "checks": [
    {
      "check": "engine/core/engine_manifest.json exists",
      "status": "PASS"
    },
    {
      "check": "engine/core/system_registry.json exists",
      "status": "PASS"
    },
    {
      "check": "content/damian/content_pack.json exists",
      "status": "PASS"
    },
    {
      "check": "content/jacobs_bane/content_pack.json exists",
      "status": "PASS"
    },
    {
      "check": "Damian appears only as content pack identity, not engine identity",
      "status": "PASS"
    },
    {
      "check": "Jacob's Bane appears as second content pack placeholder",
      "status": "PASS"
    }
  ]
}